{"qt.594.qtcharts.win32_mingw53": {"Name": "qt.594.qtcharts.win32_mingw53", "DisplayName": "Qt Charts for MinGW 5.3.0 32-bit", "Description": null, "Version": "5.9.4-0-201801211309", "ReleaseDate": "2018-01-21", "CompressedSize": "13.183MB", "UncompressedSize": "92.789MB", "DownloadableArchives": ["qtcharts-Windows-Windows_7-Mingw53-Windows-Windows_7-X86.7z"]}, "qt.594.qtcharts.win32_msvc2015": {"Name": "qt.594.qtcharts.win32_msvc2015", "DisplayName": "Qt Charts for msvc2015 32-bit", "Description": null, "Version": "5.9.4-0-201801211309", "ReleaseDate": "2018-01-21", "CompressedSize": "5.307MB", "UncompressedSize": "43.289MB", "DownloadableArchives": ["qtcharts-Windows-Windows_10-MSVC2015-Windows-Windows_10-X86.7z"]}, "qt.594.qtcharts.win64_msvc2013_64": {"Name": "qt.594.qtcharts.win64_msvc2013_64", "DisplayName": "Qt Charts for msvc2013 64-bit", "Description": null, "Version": "5.9.4-0-201801211309", "ReleaseDate": "2018-01-21", "CompressedSize": "5.257MB", "UncompressedSize": "42.265MB", "DownloadableArchives": ["qtcharts-Windows-Windows_8_1-MSVC2013-Windows-Windows_8_1-X86_64.7z"]}, "qt.594.qtcharts.win64_msvc2015_64": {"Name": "qt.594.qtcharts.win64_msvc2015_64", "DisplayName": "Qt Charts for msvc2015 64-bit", "Description": null, "Version": "5.9.4-0-201801211309", "ReleaseDate": "2018-01-21", "CompressedSize": "5.809MB", "UncompressedSize": "44.586MB", "DownloadableArchives": ["qtcharts-Windows-Windows_10-MSVC2015-Windows-Windows_10-X86_64.7z"]}, "qt.594.qtcharts.win64_msvc2017_64": {"Name": "qt.594.qtcharts.win64_msvc2017_64", "DisplayName": "Qt Charts for msvc2017 64-bit", "Description": null, "Version": "5.9.4-0-201801211309", "ReleaseDate": "2018-01-21", "CompressedSize": "5.872MB", "UncompressedSize": "44.982MB", "DownloadableArchives": ["qtcharts-Windows-Windows_10-MSVC2017-Windows-Windows_10-X86_64.7z"]}, "qt.594.qtdatavis3d.win32_mingw53": {"Name": "qt.594.qtdatavis3d.win32_mingw53", "DisplayName": "Qt Data Visualization for MinGW 5.3.0 32-bit", "Description": null, "Version": "5.9.4-0-201801211309", "ReleaseDate": "2018-01-21", "CompressedSize": "12.115MB", "UncompressedSize": "87.039MB", "DownloadableArchives": ["qtdatavis3d-Windows-Windows_7-Mingw53-Windows-Windows_7-X86.7z"]}, "qt.594.qtdatavis3d.win32_msvc2015": {"Name": "qt.594.qtdatavis3d.win32_msvc2015", "DisplayName": "Qt Data Visualization for msvc2015 32-bit", "Description": null, "Version": "5.9.4-0-201801211309", "ReleaseDate": "2018-01-21", "CompressedSize": "4.774MB", "UncompressedSize": "41.183MB", "DownloadableArchives": ["qtdatavis3d-Windows-Windows_10-MSVC2015-Windows-Windows_10-X86.7z"]}, "qt.594.qtdatavis3d.win64_msvc2013_64": {"Name": "qt.594.qtdatavis3d.win64_msvc2013_64", "DisplayName": "Qt Data Visualization for msvc2013 64-bit", "Description": null, "Version": "5.9.4-0-201801211309", "ReleaseDate": "2018-01-21", "CompressedSize": "4.627MB", "UncompressedSize": "39.727MB", "DownloadableArchives": ["qtdatavis3d-Windows-Windows_8_1-MSVC2013-Windows-Windows_8_1-X86_64.7z"]}, "qt.594.qtdatavis3d.win64_msvc2015_64": {"Name": "qt.594.qtdatavis3d.win64_msvc2015_64", "DisplayName": "Qt Data Visualization for msvc2015 64-bit", "Description": null, "Version": "5.9.4-0-201801211309", "ReleaseDate": "2018-01-21", "CompressedSize": "5.143MB", "UncompressedSize": "42.130MB", "DownloadableArchives": ["qtdatavis3d-Windows-Windows_10-MSVC2015-Windows-Windows_10-X86_64.7z"]}, "qt.594.qtdatavis3d.win64_msvc2017_64": {"Name": "qt.594.qtdatavis3d.win64_msvc2017_64", "DisplayName": "Qt Data Visualization for msvc2017 64-bit", "Description": null, "Version": "5.9.4-0-201801211309", "ReleaseDate": "2018-01-21", "CompressedSize": "5.227MB", "UncompressedSize": "42.508MB", "DownloadableArchives": ["qtdatavis3d-Windows-Windows_10-MSVC2017-Windows-Windows_10-X86_64.7z"]}, "qt.594.qtnetworkauth.win32_mingw53": {"Name": "qt.594.qtnetworkauth.win32_mingw53", "DisplayName": "Qt Network Authentication for MinGW 5.3.0 32-bit", "Description": null, "Version": "5.9.4-0-201801211309", "ReleaseDate": "2018-01-21", "CompressedSize": "1.304MB", "UncompressedSize": "8.430MB", "DownloadableArchives": ["qtnetworkauth-Windows-Windows_7-Mingw53-Windows-Windows_7-X86.7z"]}, "qt.594.qtnetworkauth.win32_msvc2015": {"Name": "qt.594.qtnetworkauth.win32_msvc2015", "DisplayName": "Qt Network Authentication for msvc2015 32-bit", "Description": null, "Version": "5.9.4-0-201801211309", "ReleaseDate": "2018-01-21", "CompressedSize": "955.358KB", "UncompressedSize": "7.670MB", "DownloadableArchives": ["qtnetworkauth-Windows-Windows_10-MSVC2015-Windows-Windows_10-X86.7z"]}, "qt.594.qtnetworkauth.win64_msvc2013_64": {"Name": "qt.594.qtnetworkauth.win64_msvc2013_64", "DisplayName": "Qt Network Authentication for msvc2013 64-bit", "Description": null, "Version": "5.9.4-0-201801211309", "ReleaseDate": "2018-01-21", "CompressedSize": "977.767KB", "UncompressedSize": "7.091MB", "DownloadableArchives": ["qtnetworkauth-Windows-Windows_8_1-MSVC2013-Windows-Windows_8_1-X86_64.7z"]}, "qt.594.qtnetworkauth.win64_msvc2015_64": {"Name": "qt.594.qtnetworkauth.win64_msvc2015_64", "DisplayName": "Qt Network Authentication for msvc2015_64-bit", "Description": null, "Version": "5.9.4-0-201801211309", "ReleaseDate": "2018-01-21", "CompressedSize": "1.065MB", "UncompressedSize": "7.817MB", "DownloadableArchives": ["qtnetworkauth-Windows-Windows_10-MSVC2015-Windows-Windows_10-X86_64.7z"]}, "qt.594.qtnetworkauth.win64_msvc2017_64": {"Name": "qt.594.qtnetworkauth.win64_msvc2017_64", "DisplayName": "Qt Network Authentication for msvc2017_64-bit", "Description": null, "Version": "5.9.4-0-201801211309", "ReleaseDate": "2018-01-21", "CompressedSize": "1.080MB", "UncompressedSize": "7.827MB", "DownloadableArchives": ["qtnetworkauth-Windows-Windows_10-MSVC2017-Windows-Windows_10-X86_64.7z"]}, "qt.594.qtpurchasing.win32_mingw53": {"Name": "qt.594.qtpurchasing.win32_mingw53", "DisplayName": "Qt Purchasing for MinGW 5.3.0 32-bit", "Description": null, "Version": "5.9.4-0-201801211309", "ReleaseDate": "2018-01-21", "CompressedSize": "713.103KB", "UncompressedSize": "4.612MB", "DownloadableArchives": ["qtpurchasing-Windows-Windows_7-Mingw53-Windows-Windows_7-X86.7z"]}, "qt.594.qtpurchasing.win32_msvc2015": {"Name": "qt.594.qtpurchasing.win32_msvc2015", "DisplayName": "Qt Location for msvc2015 32-bit", "Description": null, "Version": "5.9.4-0-201801211309", "ReleaseDate": "2018-01-21", "CompressedSize": "903.972KB", "UncompressedSize": "7.682MB", "DownloadableArchives": ["qtpurchasing-Windows-Windows_10-MSVC2015-Windows-Windows_10-X86.7z"]}, "qt.594.qtpurchasing.win64_msvc2013_64": {"Name": "qt.594.qtpurchasing.win64_msvc2013_64", "DisplayName": "Qt Purchasing for msvc2013 64-bit", "Description": null, "Version": "5.9.4-0-201801211309", "ReleaseDate": "2018-01-21", "CompressedSize": "914.909KB", "UncompressedSize": "7.136MB", "DownloadableArchives": ["qtpurchasing-Windows-Windows_8_1-MSVC2013-Windows-Windows_8_1-X86_64.7z"]}, "qt.594.qtpurchasing.win64_msvc2015_64": {"Name": "qt.594.qtpurchasing.win64_msvc2015_64", "DisplayName": "Qt Purchasing for msvc2015 64-bit", "Description": null, "Version": "5.9.4-0-201801211309", "ReleaseDate": "2018-01-21", "CompressedSize": "984.885KB", "UncompressedSize": "7.786MB", "DownloadableArchives": ["qtpurchasing-Windows-Windows_10-MSVC2015-Windows-Windows_10-X86_64.7z"]}, "qt.594.qtpurchasing.win64_msvc2017_64": {"Name": "qt.594.qtpurchasing.win64_msvc2017_64", "DisplayName": "Qt Purchasing for msvc2017 64-bit", "Description": null, "Version": "5.9.4-0-201801211309", "ReleaseDate": "2018-01-21", "CompressedSize": "1007.079KB", "UncompressedSize": "7.973MB", "DownloadableArchives": ["qtpurchasing-Windows-Windows_10-MSVC2017-Windows-Windows_10-X86_64.7z"]}, "qt.594.qtremoteobjects.win32_mingw53": {"Name": "qt.594.qtremoteobjects.win32_mingw53", "DisplayName": "Qt Remote Objects for MinGW 5.3.0 32-bit", "Description": null, "Version": "5.9.4-0-201801211309", "ReleaseDate": "2018-01-21", "CompressedSize": "2.898MB", "UncompressedSize": "17.317MB", "DownloadableArchives": ["qtremoteobjects-Windows-Windows_7-Mingw53-Windows-Windows_7-X86.7z"]}, "qt.594.qtremoteobjects.win32_msvc2015": {"Name": "qt.594.qtremoteobjects.win32_msvc2015", "DisplayName": "Qt Remote Objects for msvc2015 32-bit", "Description": null, "Version": "5.9.4-0-201801211309", "ReleaseDate": "2018-01-21", "CompressedSize": "1.883MB", "UncompressedSize": "14.471MB", "DownloadableArchives": ["qtremoteobjects-Windows-Windows_10-MSVC2015-Windows-Windows_10-X86.7z"]}, "qt.594.qtremoteobjects.win64_msvc2013_64": {"Name": "qt.594.qtremoteobjects.win64_msvc2013_64", "DisplayName": "Qt Remote Objects for msvc2013 64-bit", "Description": null, "Version": "5.9.4-0-201801211309", "ReleaseDate": "2018-01-21", "CompressedSize": "1.786MB", "UncompressedSize": "13.784MB", "DownloadableArchives": ["qtremoteobjects-Windows-Windows_8_1-MSVC2013-Windows-Windows_8_1-X86_64.7z"]}, "qt.594.qtremoteobjects.win64_msvc2015_64": {"Name": "qt.594.qtremoteobjects.win64_msvc2015_64", "DisplayName": "Qt Remote Objects for msvc2015_64-bit", "Description": null, "Version": "5.9.4-0-201801211309", "ReleaseDate": "2018-01-21", "CompressedSize": "2.006MB", "UncompressedSize": "15.020MB", "DownloadableArchives": ["qtremoteobjects-Windows-Windows_10-MSVC2015-Windows-Windows_10-X86_64.7z"]}, "qt.594.qtremoteobjects.win64_msvc2017_64": {"Name": "qt.594.qtremoteobjects.win64_msvc2017_64", "DisplayName": "Qt Remote Objects for msvc2017_64-bit", "Description": null, "Version": "5.9.4-0-201801211309", "ReleaseDate": "2018-01-21", "CompressedSize": "2.060MB", "UncompressedSize": "15.018MB", "DownloadableArchives": ["qtremoteobjects-Windows-Windows_10-MSVC2017-Windows-Windows_10-X86_64.7z"]}, "qt.594.qtscript.win32_mingw53": {"Name": "qt.594.qtscript.win32_mingw53", "DisplayName": "Qt Script for MinGW 5.3.0 32-bit", "Description": null, "Version": "5.9.4-0-201801211309", "ReleaseDate": "2018-01-21", "CompressedSize": "21.815MB", "UncompressedSize": "149.960MB", "DownloadableArchives": ["qtscript-Windows-Windows_7-Mingw53-Windows-Windows_7-X86.7z"]}, "qt.594.qtscript.win32_msvc2015": {"Name": "qt.594.qtscript.win32_msvc2015", "DisplayName": "Qt Script for msvc2015 32-bit", "Description": null, "Version": "5.9.4-0-201801211309", "ReleaseDate": "2018-01-21", "CompressedSize": "7.105MB", "UncompressedSize": "54.243MB", "DownloadableArchives": ["qtscript-Windows-Windows_10-MSVC2015-Windows-Windows_10-X86.7z"]}, "qt.594.qtscript.win64_msvc2013_64": {"Name": "qt.594.qtscript.win64_msvc2013_64", "DisplayName": "Qt Script for msvc2013 64-bit", "Description": null, "Version": "5.9.4-0-201801211309", "ReleaseDate": "2018-01-21", "CompressedSize": "5.818MB", "UncompressedSize": "48.738MB", "DownloadableArchives": ["qtscript-Windows-Windows_8_1-MSVC2013-Windows-Windows_8_1-X86_64.7z"]}, "qt.594.qtscript.win64_msvc2015_64": {"Name": "qt.594.qtscript.win64_msvc2015_64", "DisplayName": "Qt Script for msvc2015 64-bit", "Description": null, "Version": "5.9.4-0-201801211309", "ReleaseDate": "2018-01-21", "CompressedSize": "7.042MB", "UncompressedSize": "52.177MB", "DownloadableArchives": ["qtscript-Windows-Windows_10-MSVC2015-Windows-Windows_10-X86_64.7z"]}, "qt.594.qtscript.win64_msvc2017_64": {"Name": "qt.594.qtscript.win64_msvc2017_64", "DisplayName": "Qt Script for msvc2017 64-bit", "Description": null, "Version": "5.9.4-0-201801211309", "ReleaseDate": "2018-01-21", "CompressedSize": "6.847MB", "UncompressedSize": "51.417MB", "DownloadableArchives": ["qtscript-Windows-Windows_10-MSVC2017-Windows-Windows_10-X86_64.7z"]}, "qt.594.qtspeech.win32_mingw53": {"Name": "qt.594.qtspeech.win32_mingw53", "DisplayName": "Qt Speech for MinGW 5.3.0 32-bit", "Description": null, "Version": "5.9.4-0-201801211309", "ReleaseDate": "2018-01-21", "CompressedSize": "738.823KB", "UncompressedSize": "4.418MB", "DownloadableArchives": ["qtspeech-Windows-Windows_7-Mingw53-Windows-Windows_7-X86.7z"]}, "qt.594.qtspeech.win32_msvc2015": {"Name": "qt.594.qtspeech.win32_msvc2015", "DisplayName": "Qt Speech for msvc2015 32-bit", "Description": null, "Version": "5.9.4-0-201801211309", "ReleaseDate": "2018-01-21", "CompressedSize": "1.302MB", "UncompressedSize": "9.653MB", "DownloadableArchives": ["qtspeech-Windows-Windows_10-MSVC2015-Windows-Windows_10-X86.7z"]}, "qt.594.qtspeech.win64_msvc2013_64": {"Name": "qt.594.qtspeech.win64_msvc2013_64", "DisplayName": "Qt Speech for msvc2013 64-bit", "Description": null, "Version": "5.9.4-0-201801211309", "ReleaseDate": "2018-01-21", "CompressedSize": "1.242MB", "UncompressedSize": "9.230MB", "DownloadableArchives": ["qtspeech-Windows-Windows_8_1-MSVC2013-Windows-Windows_8_1-X86_64.7z"]}, "qt.594.qtspeech.win64_msvc2015_64": {"Name": "qt.594.qtspeech.win64_msvc2015_64", "DisplayName": "Qt Speech for msvc2015_64-bit", "Description": null, "Version": "5.9.4-0-201801211309", "ReleaseDate": "2018-01-21", "CompressedSize": "1.338MB", "UncompressedSize": "9.769MB", "DownloadableArchives": ["qtspeech-Windows-Windows_10-MSVC2015-Windows-Windows_10-X86_64.7z"]}, "qt.594.qtspeech.win64_msvc2017_64": {"Name": "qt.594.qtspeech.win64_msvc2017_64", "DisplayName": "Qt Speech for msvc2017_64-bit", "Description": null, "Version": "5.9.4-0-201801211309", "ReleaseDate": "2018-01-21", "CompressedSize": "1.381MB", "UncompressedSize": "10.096MB", "DownloadableArchives": ["qtspeech-Windows-Windows_10-MSVC2017-Windows-Windows_10-X86_64.7z"]}, "qt.594.qtvirtualkeyboard.win32_mingw53": {"Name": "qt.594.qtvirtualkeyboard.win32_mingw53", "DisplayName": "Qt Virtual Keyboard for MinGW 5.3.0 32-bit", "Description": null, "Version": "5.9.4-0-201801211309", "ReleaseDate": "2018-01-21", "CompressedSize": "3.190MB", "UncompressedSize": "19.642MB", "DownloadableArchives": ["qtvirtualkeyboard-Windows-Windows_7-Mingw53-Windows-Windows_7-X86.7z"]}, "qt.594.qtvirtualkeyboard.win32_msvc2015": {"Name": "qt.594.qtvirtualkeyboard.win32_msvc2015", "DisplayName": "Qt Virtual Keyboard for msvc2015 32-bit", "Description": null, "Version": "5.9.4-0-201801211309", "ReleaseDate": "2018-01-21", "CompressedSize": "1.972MB", "UncompressedSize": "14.356MB", "DownloadableArchives": ["qtvirtualkeyboard-Windows-Windows_10-MSVC2015-Windows-Windows_10-X86.7z"]}, "qt.594.qtvirtualkeyboard.win64_msvc2013_64": {"Name": "qt.594.qtvirtualkeyboard.win64_msvc2013_64", "DisplayName": "Qt Virtual Keyboard for msvc2013 64-bit", "Description": null, "Version": "5.9.4-0-201801211309", "ReleaseDate": "2018-01-21", "CompressedSize": "1.959MB", "UncompressedSize": "14.383MB", "DownloadableArchives": ["qtvirtualkeyboard-Windows-Windows_8_1-MSVC2013-Windows-Windows_8_1-X86_64.7z"]}, "qt.594.qtvirtualkeyboard.win64_msvc2015_64": {"Name": "qt.594.qtvirtualkeyboard.win64_msvc2015_64", "DisplayName": "Qt Virtual Keyboard for msvc2015 64-bit", "Description": null, "Version": "5.9.4-0-201801211309", "ReleaseDate": "2018-01-21", "CompressedSize": "2.035MB", "UncompressedSize": "14.624MB", "DownloadableArchives": ["qtvirtualkeyboard-Windows-Windows_10-MSVC2015-Windows-Windows_10-X86_64.7z"]}, "qt.594.qtvirtualkeyboard.win64_msvc2017_64": {"Name": "qt.594.qtvirtualkeyboard.win64_msvc2017_64", "DisplayName": "Qt Virtual Keyboard for msvc2017 64-bit", "Description": null, "Version": "5.9.4-0-201801211309", "ReleaseDate": "2018-01-21", "CompressedSize": "2.089MB", "UncompressedSize": "14.968MB", "DownloadableArchives": ["qtvirtualkeyboard-Windows-Windows_10-MSVC2017-Windows-Windows_10-X86_64.7z"]}, "qt.594.qtwebengine.win32_msvc2015": {"Name": "qt.594.qtwebengine.win32_msvc2015", "DisplayName": "Qt WebEngine for msvc2015 32-bit", "Description": null, "Version": "5.9.4-0-201801211309", "ReleaseDate": "2018-01-21", "CompressedSize": "108.658MB", "UncompressedSize": "849.639MB", "DownloadableArchives": ["qtwebengine-Windows-Windows_10-MSVC2015-Windows-Windows_10-X86.7z"]}, "qt.594.qtwebengine.win64_msvc2015_64": {"Name": "qt.594.qtwebengine.win64_msvc2015_64", "DisplayName": "Qt WebEngine for msvc2015 64-bit", "Description": null, "Version": "5.9.4-0-201801211309", "ReleaseDate": "2018-01-21", "CompressedSize": "293.328MB", "UncompressedSize": "2.463GB", "DownloadableArchives": ["qtwebengine-Windows-Windows_10-MSVC2015-Windows-Windows_10-X86_64.7z"]}, "qt.594.qtwebengine.win64_msvc2017_64": {"Name": "qt.594.qtwebengine.win64_msvc2017_64", "DisplayName": "Qt WebEngine for msvc2017 64-bit", "Description": null, "Version": "5.9.4-0-201801211309", "ReleaseDate": "2018-01-21", "CompressedSize": "275.834MB", "UncompressedSize": "2.087GB", "DownloadableArchives": ["qtwebengine-Windows-Windows_10-MSVC2017-Windows-Windows_10-X86_64.7z"]}, "qt.594.win32_mingw53": {"Name": "qt.594.win32_mingw53", "DisplayName": "MinGW 5.3.0 32 bit", "Description": "Qt 5.9.4 Prebuilt Components for MinGW 5.3.0 32-bit", "Version": "5.9.4-0-201801211309", "ReleaseDate": "2018-01-21", "CompressedSize": "523.211MB", "UncompressedSize": "3.387GB", "DownloadableArchives": ["qtbase-Windows-Windows_7-Mingw53-Windows-Windows_7-X86.7z", "qtconnectivity-Windows-Windows_7-Mingw53-Windows-Windows_7-X86.7z", "qtactiveqt-Windows-Windows_7-Mingw53-Windows-Windows_7-X86.7z", "qtmultimedia-Windows-Windows_7-Mingw53-Windows-Windows_7-X86.7z", "qttranslations-Windows-Windows_7-Mingw53-Windows-Windows_7-X86.7z", "qtgraphicaleffects-Windows-Windows_7-Mingw53-Windows-Windows_7-X86.7z", "qtsvg-Windows-Windows_7-Mingw53-Windows-Windows_7-X86.7z", "qtdeclarative-Windows-Windows_7-Mingw53-Windows-Windows_7-X86.7z", "qtwinextras-Windows-Windows_7-Mingw53-Windows-Windows_7-X86.7z", "qtimageformats-Windows-Windows_7-Mingw53-Windows-Windows_7-X86.7z", "qttools-Windows-Windows_7-Mingw53-Windows-Windows_7-X86.7z", "qtxmlpatterns-Windows-Windows_7-Mingw53-Windows-Windows_7-X86.7z", "qtsensors-Windows-Windows_7-Mingw53-Windows-Windows_7-X86.7z", "qtwebsockets-Windows-Windows_7-Mingw53-Windows-Windows_7-X86.7z", "qtwebchannel-Windows-Windows_7-Mingw53-Windows-Windows_7-X86.7z", "qtlocation-Windows-Windows_7-Mingw53-Windows-Windows_7-X86.7z", "qtserialport-Windows-Windows_7-Mingw53-Windows-Windows_7-X86.7z", "qtquickcontrols-Windows-Windows_7-Mingw53-Windows-Windows_7-X86.7z", "qtquickcontrols2-Windows-Windows_7-Mingw53-Windows-Windows_7-X86.7z", "qt3d-Windows-Windows_7-Mingw53-Windows-Windows_7-X86.7z", "qtcanvas3d-Windows-Windows_7-Mingw53-Windows-Windows_7-X86.7z", "qtserialbus-Windows-Windows_7-Mingw53-Windows-Windows_7-X86.7z", "qtscxml-Windows-Windows_7-Mingw53-Windows-Windows_7-X86.7z", "qtgamepad-Windows-Windows_7-Mingw53-Windows-Windows_7-X86.7z", "i686-5.3.0-release-posix-dwarf-rt_v4-rev0-runtime.7z", "d3dcompiler_47-x86.7z", "opengl32sw-32-mesa_12_0_rc2.7z"]}, "qt.594.win32_msvc2015": {"Name": "qt.594.win32_msvc2015", "DisplayName": "msvc2015 32-bit", "Description": "Qt 5.9.4 Prebuilt Components for msvc2015 32-bit", "Version": "5.9.4-0-201801211309", "ReleaseDate": "2018-01-21", "CompressedSize": "304.946MB", "UncompressedSize": "2.329GB", "DownloadableArchives": ["qtbase-Windows-Windows_10-MSVC2015-Windows-Windows_10-X86.7z", "qtconnectivity-Windows-Windows_10-MSVC2015-Windows-Windows_10-X86.7z", "qtactiveqt-Windows-Windows_10-MSVC2015-Windows-Windows_10-X86.7z", "qtmultimedia-Windows-Windows_10-MSVC2015-Windows-Windows_10-X86.7z", "qttranslations-Windows-Windows_10-MSVC2015-Windows-Windows_10-X86.7z", "qtgraphicaleffects-Windows-Windows_10-MSVC2015-Windows-Windows_10-X86.7z", "qtsvg-Windows-Windows_10-MSVC2015-Windows-Windows_10-X86.7z", "qtdeclarative-Windows-Windows_10-MSVC2015-Windows-Windows_10-X86.7z", "qtwinextras-Windows-Windows_10-MSVC2015-Windows-Windows_10-X86.7z", "qtimageformats-Windows-Windows_10-MSVC2015-Windows-Windows_10-X86.7z", "qttools-Windows-Windows_10-MSVC2015-Windows-Windows_10-X86.7z", "qtxmlpatterns-Windows-Windows_10-MSVC2015-Windows-Windows_10-X86.7z", "qtsensors-Windows-Windows_10-MSVC2015-Windows-Windows_10-X86.7z", "qtwebsockets-Windows-Windows_10-MSVC2015-Windows-Windows_10-X86.7z", "qtwebchannel-Windows-Windows_10-MSVC2015-Windows-Windows_10-X86.7z", "qtlocation-Windows-Windows_10-MSVC2015-Windows-Windows_10-X86.7z", "qtserialport-Windows-Windows_10-MSVC2015-Windows-Windows_10-X86.7z", "qtquickcontrols-Windows-Windows_10-MSVC2015-Windows-Windows_10-X86.7z", "qtquickcontrols2-Windows-Windows_10-MSVC2015-Windows-Windows_10-X86.7z", "qt3d-Windows-Windows_10-MSVC2015-Windows-Windows_10-X86.7z", "qtcanvas3d-Windows-Windows_10-MSVC2015-Windows-Windows_10-X86.7z", "qtwebview-Windows-Windows_10-MSVC2015-Windows-Windows_10-X86.7z", "qtserialbus-Windows-Windows_10-MSVC2015-Windows-Windows_10-X86.7z", "qtscxml-Windows-Windows_10-MSVC2015-Windows-Windows_10-X86.7z", "qtgamepad-Windows-Windows_10-MSVC2015-Windows-Windows_10-X86.7z", "d3dcompiler_47-x86.7z", "opengl32sw-32-mesa_12_0_rc2.7z"]}, "qt.594.win64_msvc2013_64": {"Name": "qt.594.win64_msvc2013_64", "DisplayName": "msvc2013 64-bit", "Description": "Qt 5.9.4 Prebuilt Components for msvc2013 64-bit", "Version": "5.9.4-0-201801211309", "ReleaseDate": "2018-01-21", "CompressedSize": "280.692MB", "UncompressedSize": "2.173GB", "DownloadableArchives": ["qtbase-Windows-Windows_8_1-MSVC2013-Windows-Windows_8_1-X86_64.7z", "qtconnectivity-Windows-Windows_8_1-MSVC2013-Windows-Windows_8_1-X86_64.7z", "qtactiveqt-Windows-Windows_8_1-MSVC2013-Windows-Windows_8_1-X86_64.7z", "qtmultimedia-Windows-Windows_8_1-MSVC2013-Windows-Windows_8_1-X86_64.7z", "qttranslations-Windows-Windows_8_1-MSVC2013-Windows-Windows_8_1-X86_64.7z", "qtgraphicaleffects-Windows-Windows_8_1-MSVC2013-Windows-Windows_8_1-X86_64.7z", "qtsvg-Windows-Windows_8_1-MSVC2013-Windows-Windows_8_1-X86_64.7z", "qtdeclarative-Windows-Windows_8_1-MSVC2013-Windows-Windows_8_1-X86_64.7z", "qtwinextras-Windows-Windows_8_1-MSVC2013-Windows-Windows_8_1-X86_64.7z", "qtimageformats-Windows-Windows_8_1-MSVC2013-Windows-Windows_8_1-X86_64.7z", "qttools-Windows-Windows_8_1-MSVC2013-Windows-Windows_8_1-X86_64.7z", "qtxmlpatterns-Windows-Windows_8_1-MSVC2013-Windows-Windows_8_1-X86_64.7z", "qtsensors-Windows-Windows_8_1-MSVC2013-Windows-Windows_8_1-X86_64.7z", "qtwebsockets-Windows-Windows_8_1-MSVC2013-Windows-Windows_8_1-X86_64.7z", "qtwebchannel-Windows-Windows_8_1-MSVC2013-Windows-Windows_8_1-X86_64.7z", "qtlocation-Windows-Windows_8_1-MSVC2013-Windows-Windows_8_1-X86_64.7z", "qtserialport-Windows-Windows_8_1-MSVC2013-Windows-Windows_8_1-X86_64.7z", "qtquickcontrols-Windows-Windows_8_1-MSVC2013-Windows-Windows_8_1-X86_64.7z", "qtquickcontrols2-Windows-Windows_8_1-MSVC2013-Windows-Windows_8_1-X86_64.7z", "qt3d-Windows-Windows_8_1-MSVC2013-Windows-Windows_8_1-X86_64.7z", "qtcanvas3d-Windows-Windows_8_1-MSVC2013-Windows-Windows_8_1-X86_64.7z", "qtserialbus-Windows-Windows_8_1-MSVC2013-Windows-Windows_8_1-X86_64.7z", "qtscxml-Windows-Windows_8_1-MSVC2013-Windows-Windows_8_1-X86_64.7z", "qtgamepad-Windows-Windows_8_1-MSVC2013-Windows-Windows_8_1-X86_64.7z", "d3dcompiler_47-x64.7z", "opengl32sw-64-mesa_12_0_rc2.7z"]}, "qt.594.win64_msvc2015_64": {"Name": "qt.594.win64_msvc2015_64", "DisplayName": "msvc2015 64-bit", "Description": "Qt 5.9.4 Prebuilt Components for msvc2015 64-bit", "Version": "5.9.4-0-201801211309", "ReleaseDate": "2018-01-21", "CompressedSize": "327.292MB", "UncompressedSize": "2.426GB", "DownloadableArchives": ["qtbase-Windows-Windows_10-MSVC2015-Windows-Windows_10-X86_64.7z", "qtconnectivity-Windows-Windows_10-MSVC2015-Windows-Windows_10-X86_64.7z", "qtactiveqt-Windows-Windows_10-MSVC2015-Windows-Windows_10-X86_64.7z", "qtmultimedia-Windows-Windows_10-MSVC2015-Windows-Windows_10-X86_64.7z", "qttranslations-Windows-Windows_10-MSVC2015-Windows-Windows_10-X86_64.7z", "qtgraphicaleffects-Windows-Windows_10-MSVC2015-Windows-Windows_10-X86_64.7z", "qtsvg-Windows-Windows_10-MSVC2015-Windows-Windows_10-X86_64.7z", "qtdeclarative-Windows-Windows_10-MSVC2015-Windows-Windows_10-X86_64.7z", "qtwinextras-Windows-Windows_10-MSVC2015-Windows-Windows_10-X86_64.7z", "qtimageformats-Windows-Windows_10-MSVC2015-Windows-Windows_10-X86_64.7z", "qttools-Windows-Windows_10-MSVC2015-Windows-Windows_10-X86_64.7z", "qtxmlpatterns-Windows-Windows_10-MSVC2015-Windows-Windows_10-X86_64.7z", "qtsensors-Windows-Windows_10-MSVC2015-Windows-Windows_10-X86_64.7z", "qtwebsockets-Windows-Windows_10-MSVC2015-Windows-Windows_10-X86_64.7z", "qtwebchannel-Windows-Windows_10-MSVC2015-Windows-Windows_10-X86_64.7z", "qtlocation-Windows-Windows_10-MSVC2015-Windows-Windows_10-X86_64.7z", "qtserialport-Windows-Windows_10-MSVC2015-Windows-Windows_10-X86_64.7z", "qtquickcontrols-Windows-Windows_10-MSVC2015-Windows-Windows_10-X86_64.7z", "qtquickcontrols2-Windows-Windows_10-MSVC2015-Windows-Windows_10-X86_64.7z", "qt3d-Windows-Windows_10-MSVC2015-Windows-Windows_10-X86_64.7z", "qtcanvas3d-Windows-Windows_10-MSVC2015-Windows-Windows_10-X86_64.7z", "qtwebview-Windows-Windows_10-MSVC2015-Windows-Windows_10-X86_64.7z", "qtserialbus-Windows-Windows_10-MSVC2015-Windows-Windows_10-X86_64.7z", "qtscxml-Windows-Windows_10-MSVC2015-Windows-Windows_10-X86_64.7z", "qtgamepad-Windows-Windows_10-MSVC2015-Windows-Windows_10-X86_64.7z", "d3dcompiler_47-x64.7z", "opengl32sw-64-mesa_12_0_rc2.7z"]}, "qt.594.win64_msvc2017_64": {"Name": "qt.594.win64_msvc2017_64", "DisplayName": "msvc2017 64-bit", "Description": "Qt 5.9.4 Prebuilt Components for msvc2017 64-bit", "Version": "5.9.4-0-201801211309", "ReleaseDate": "2018-01-21", "CompressedSize": "328.257MB", "UncompressedSize": "2.392GB", "DownloadableArchives": ["qtbase-Windows-Windows_10-MSVC2017-Windows-Windows_10-X86_64.7z", "qtconnectivity-Windows-Windows_10-MSVC2017-Windows-Windows_10-X86_64.7z", "qtactiveqt-Windows-Windows_10-MSVC2017-Windows-Windows_10-X86_64.7z", "qtmultimedia-Windows-Windows_10-MSVC2017-Windows-Windows_10-X86_64.7z", "qttranslations-Windows-Windows_10-MSVC2017-Windows-Windows_10-X86_64.7z", "qtgraphicaleffects-Windows-Windows_10-MSVC2017-Windows-Windows_10-X86_64.7z", "qtsvg-Windows-Windows_10-MSVC2017-Windows-Windows_10-X86_64.7z", "qtdeclarative-Windows-Windows_10-MSVC2017-Windows-Windows_10-X86_64.7z", "qtwinextras-Windows-Windows_10-MSVC2017-Windows-Windows_10-X86_64.7z", "qtimageformats-Windows-Windows_10-MSVC2017-Windows-Windows_10-X86_64.7z", "qttools-Windows-Windows_10-MSVC2017-Windows-Windows_10-X86_64.7z", "qtxmlpatterns-Windows-Windows_10-MSVC2017-Windows-Windows_10-X86_64.7z", "qtsensors-Windows-Windows_10-MSVC2017-Windows-Windows_10-X86_64.7z", "qtwebsockets-Windows-Windows_10-MSVC2017-Windows-Windows_10-X86_64.7z", "qtwebchannel-Windows-Windows_10-MSVC2017-Windows-Windows_10-X86_64.7z", "qtlocation-Windows-Windows_10-MSVC2017-Windows-Windows_10-X86_64.7z", "qtserialport-Windows-Windows_10-MSVC2017-Windows-Windows_10-X86_64.7z", "qtquickcontrols-Windows-Windows_10-MSVC2017-Windows-Windows_10-X86_64.7z", "qtquickcontrols2-Windows-Windows_10-MSVC2017-Windows-Windows_10-X86_64.7z", "qt3d-Windows-Windows_10-MSVC2017-Windows-Windows_10-X86_64.7z", "qtcanvas3d-Windows-Windows_10-MSVC2017-Windows-Windows_10-X86_64.7z", "qtwebview-Windows-Windows_10-MSVC2017-Windows-Windows_10-X86_64.7z", "qtserialbus-Windows-Windows_10-MSVC2017-Windows-Windows_10-X86_64.7z", "qtscxml-Windows-Windows_10-MSVC2017-Windows-Windows_10-X86_64.7z", "qtgamepad-Windows-Windows_10-MSVC2017-Windows-Windows_10-X86_64.7z", "d3dcompiler_47-x64.7z", "opengl32sw-64-mesa_12_0_rc2.7z"]}}