{"qt.tools.openssl.src": {"Name": "qt.tools.openssl.src", "DisplayName": "OpenSSL source code", "Description": "OpenSSL source code.<br><br>Due to import and export restrictions in some parts of the world, developers wishing to use SSL communication in their deployed applications should either ensure that their users have the appropriate libraries installed, or they should consult a suitably qualified legal professional to ensure that applications using code from the OpenSSL project are correctly certified for import and export in relevant regions of the world.<br><br>Note: Qt installer doesn't set up OpenSSL environment. User needs to define the path and environment variables.", "Version": "1.1.1-10", "ReleaseDate": "2021-02-26", "CompressedSize": "7.126MB", "UncompressedSize": "39.403MB", "DownloadableArchives": ["openssl-1.1.1j.7z"]}}